<?xml version='1.0' encoding='utf-8'?>
<products>
    <product>
        <kodas>10902</kodas>
        <ean>5908268747109</ean>
        <stock_local>0</stock_local>
        <stock_supplier_fast>0</stock_supplier_fast>
        <stock_supplier_slow>0</stock_supplier_slow>
        <total_stock>0</total_stock>
    </product>
    <product>
        <kodas>13369</kodas>
        <ean>5902963010001</ean>
        <stock_local>0</stock_local>
        <stock_supplier_fast>0</stock_supplier_fast>
        <stock_supplier_slow>15</stock_supplier_slow>
        <total_stock>15</total_stock>
    </product>
    <product>
        <kodas>14617</kodas>
        <ean>5902963009999</ean>
        <stock_local>0</stock_local>
        <stock_supplier_fast>0</stock_supplier_fast>
        <stock_supplier_slow>5</stock_supplier_slow>
        <total_stock>5</total_stock>
    </product>
    <product>
        <kodas>15194</kodas>
        <ean>5902963011466</ean>
        <stock_local>0</stock_local>
        <stock_supplier_fast>0</stock_supplier_fast>
        <stock_supplier_slow>5</stock_supplier_slow>
        <total_stock>5</total_stock>
    </product>
    <product>
        <kodas>15195</kodas>
        <ean>5902963008992</ean>
        <stock_local>0</stock_local>
        <stock_supplier_fast>0</stock_supplier_fast>
        <stock_supplier_slow>0</stock_supplier_slow>
        <total_stock>0</total_stock>
    </product>
    <product>
        <kodas>16430</kodas>
        <ean>4052396001525</ean>
        <stock_local>0</stock_local>
        <stock_supplier_fast>0</stock_supplier_fast>
        <stock_supplier_slow>0</stock_supplier_slow>
        <total_stock>0</total_stock>
    </product>
    <product>
        <kodas>17186</kodas>
        <ean>5902675040518</ean>
        <stock_local>0</stock_local>
        <stock_supplier_fast>0</stock_supplier_fast>
        <stock_supplier_slow>0</stock_supplier_slow>
        <total_stock>0</total_stock>
    </product>
    <product>
        <kodas>21538</kodas>
        <ean>5902963008879</ean>
        <stock_local>0</stock_local>
        <stock_supplier_fast>0</stock_supplier_fast>
        <stock_supplier_slow>5</stock_supplier_slow>
        <total_stock>5</total_stock>
    </product>
    <product>
        <kodas>21843</kodas>
        <ean>4052396092899</ean>
        <stock_local>0</stock_local>
        <stock_supplier_fast>0</stock_supplier_fast>
        <stock_supplier_slow>5</stock_supplier_slow>
        <total_stock>5</total_stock>
    </product>
    <product>
        <kodas>24811</kodas>
        <ean>5900694650053</ean>
        <stock_local>0</stock_local>
        <stock_supplier_fast>0</stock_supplier_fast>
        <stock_supplier_slow>0</stock_supplier_slow>
        <total_stock>0</total_stock>
    </product>
    <product>
        <kodas>25583</kodas>
        <ean>5901912243750</ean>
        <stock_local>0</stock_local>
        <stock_supplier_fast>0</stock_supplier_fast>
        <stock_supplier_slow>0</stock_supplier_slow>
        <total_stock>0</total_stock>
    </product>
    <product>
        <kodas>27070</kodas>
        <ean>5712854125215</ean>
        <stock_local>0</stock_local>
        <stock_supplier_fast>190</stock_supplier_fast>
        <stock_supplier_slow>0</stock_supplier_slow>
        <total_stock>190</total_stock>
    </product>
    <product>
        <kodas>3151</kodas>
        <stock_local>0</stock_local>
        <stock_supplier_fast>0</stock_supplier_fast>
        <stock_supplier_slow>15</stock_supplier_slow>
        <total_stock>15</total_stock>
    </product>
    <product>
        <kodas>3741</kodas>
        <ean>5710409102001</ean>
        <stock_local>0</stock_local>
        <stock_supplier_fast>16</stock_supplier_fast>
        <stock_supplier_slow>0</stock_supplier_slow>
        <total_stock>16</total_stock>
    </product>
    <product>
        <kodas>37P3097</kodas>
        <ean>5055166349970</ean>
        <stock_local>0</stock_local>
        <stock_supplier_fast>35</stock_supplier_fast>
        <stock_supplier_slow>0</stock_supplier_slow>
        <total_stock>35</total_stock>
    </product>
    <product>
        <kodas>3808</kodas>
        <ean>5710409104333</ean>
        <stock_local>0</stock_local>
        <stock_supplier_fast>79</stock_supplier_fast>
        <stock_supplier_slow>0</stock_supplier_slow>
        <total_stock>79</total_stock>
    </product>
    <product>
        <kodas>3988</kodas>
        <ean>5710409109918</ean>
        <stock_local>0</stock_local>
        <stock_supplier_fast>52</stock_supplier_fast>
        <stock_supplier_slow>0</stock_supplier_slow>
        <total_stock>52</total_stock>
    </product>
    <product>
        <kodas>3989</kodas>
        <ean>5710409109925</ean>
        <stock_local>0</stock_local>
        <stock_supplier_fast>22</stock_supplier_fast>
        <stock_supplier_slow>0</stock_supplier_slow>
        <total_stock>22</total_stock>
    </product>
    <product>
        <kodas>3990</kodas>
        <ean>5710409109932</ean>
        <stock_local>0</stock_local>
        <stock_supplier_fast>64</stock_supplier_fast>
        <stock_supplier_slow>0</stock_supplier_slow>
        <total_stock>64</total_stock>
    </product>
    <product>
        <kodas>3991</kodas>
        <ean>5710409109949</ean>
        <stock_local>0</stock_local>
        <stock_supplier_fast>67</stock_supplier_fast>
        <stock_supplier_slow>0</stock_supplier_slow>
        <total_stock>67</total_stock>
    </product>
    <product>
        <kodas>40315</kodas>
        <ean>3760039940315</ean>
        <stock_local>0</stock_local>
        <stock_supplier_fast>67</stock_supplier_fast>
        <stock_supplier_slow>0</stock_supplier_slow>
        <total_stock>67</total_stock>
    </product>
    <product>
        <kodas>40490</kodas>
        <ean>3760039940490</ean>
        <stock_local>0</stock_local>
        <stock_supplier_fast>31</stock_supplier_fast>
        <stock_supplier_slow>0</stock_supplier_slow>
        <total_stock>31</total_stock>
    </product>
    <product>
        <kodas>4106</kodas>
        <ean>5710409103374</ean>
        <stock_local>0</stock_local>
        <stock_supplier_fast>74</stock_supplier_fast>
        <stock_supplier_slow>0</stock_supplier_slow>
        <total_stock>74</total_stock>
    </product>
    <product>
        <kodas>4109</kodas>
        <ean>5710409103541</ean>
        <stock_local>0</stock_local>
        <stock_supplier_fast>555</stock_supplier_fast>
        <stock_supplier_slow>0</stock_supplier_slow>
        <total_stock>555</total_stock>
    </product>
    <product>
        <kodas>4120</kodas>
        <ean>5710409103688</ean>
        <stock_local>0</stock_local>
        <stock_supplier_fast>156</stock_supplier_fast>
        <stock_supplier_slow>0</stock_supplier_slow>
        <total_stock>156</total_stock>
    </product>
    <product>
        <kodas>4184</kodas>
        <ean>5710409104210</ean>
        <stock_local>0</stock_local>
        <stock_supplier_fast>63</stock_supplier_fast>
        <stock_supplier_slow>0</stock_supplier_slow>
        <total_stock>63</total_stock>
    </product>
    <product>
        <kodas>4200</kodas>
        <ean>5710409104722</ean>
        <stock_local>0</stock_local>
        <stock_supplier_fast>112</stock_supplier_fast>
        <stock_supplier_slow>0</stock_supplier_slow>
        <total_stock>112</total_stock>
    </product>
    <product>
        <kodas>4238</kodas>
        <ean>5710409104739</ean>
        <stock_local>0</stock_local>
        <stock_supplier_fast>111</stock_supplier_fast>
        <stock_supplier_slow>0</stock_supplier_slow>
        <total_stock>111</total_stock>
    </product>
    <product>
        <kodas>4241</kodas>
        <ean>5710409105224</ean>
        <stock_local>0</stock_local>
        <stock_supplier_fast>95</stock_supplier_fast>
        <stock_supplier_slow>0</stock_supplier_slow>
        <total_stock>95</total_stock>
    </product>
    <product>
        <kodas>4244</kodas>
        <ean>5710409105477</ean>
        <stock_local>0</stock_local>
        <stock_supplier_fast>31</stock_supplier_fast>
        <stock_supplier_slow>0</stock_supplier_slow>
        <total_stock>31</total_stock>
    </product>
    <product>
        <kodas>4246</kodas>
        <ean>5710409105590</ean>
        <stock_local>0</stock_local>
        <stock_supplier_fast>479</stock_supplier_fast>
        <stock_supplier_slow>0</stock_supplier_slow>
        <total_stock>479</total_stock>
    </product>
    <product>
        <kodas>4261</kodas>
        <ean>5710409106795</ean>
        <stock_local>0</stock_local>
        <stock_supplier_fast>20</stock_supplier_fast>
        <stock_supplier_slow>0</stock_supplier_slow>
        <total_stock>20</total_stock>
    </product>
    <product>
        <kodas>4262</kodas>
        <ean>5710409106801</ean>
        <stock_local>0</stock_local>
        <stock_supplier_fast>24</stock_supplier_fast>
        <stock_supplier_slow>0</stock_supplier_slow>
        <total_stock>24</total_stock>
    </product>
    <product>
        <kodas>4264</kodas>
        <ean>5710409106825</ean>
        <stock_local>0</stock_local>
        <stock_supplier_fast>60</stock_supplier_fast>
        <stock_supplier_slow>0</stock_supplier_slow>
        <total_stock>60</total_stock>
    </product>
    <product>
        <kodas>4265</kodas>
        <ean>5710409106832</ean>
        <stock_local>0</stock_local>
        <stock_supplier_fast>98</stock_supplier_fast>
        <stock_supplier_slow>0</stock_supplier_slow>
        <total_stock>98</total_stock>
    </product>
    <product>
        <kodas>4282</kodas>
        <ean>5710409107518</ean>
        <stock_local>0</stock_local>
        <stock_supplier_fast>532</stock_supplier_fast>
        <stock_supplier_slow>0</stock_supplier_slow>
        <total_stock>532</total_stock>
    </product>
    <product>
        <kodas>4283</kodas>
        <ean>5710409107525</ean>
        <stock_local>0</stock_local>
        <stock_supplier_fast>95</stock_supplier_fast>
        <stock_supplier_slow>0</stock_supplier_slow>
        <total_stock>95</total_stock>
    </product>
    <product>
        <kodas>4284</kodas>
        <ean>5710409107532</ean>
        <stock_local>0</stock_local>
        <stock_supplier_fast>683</stock_supplier_fast>
        <stock_supplier_slow>0</stock_supplier_slow>
        <total_stock>683</total_stock>
    </product>
    <product>
        <kodas>4285</kodas>
        <ean>5710409107549</ean>
        <stock_local>0</stock_local>
        <stock_supplier_fast>20</stock_supplier_fast>
        <stock_supplier_slow>0</stock_supplier_slow>
        <total_stock>20</total_stock>
    </product>
    <product>
        <kodas>4286</kodas>
        <ean>5710409107556</ean>
        <stock_local>0</stock_local>
        <stock_supplier_fast>85</stock_supplier_fast>
        <stock_supplier_slow>0</stock_supplier_slow>
        <total_stock>85</total_stock>
    </product>
    <product>
        <kodas>4287</kodas>
        <ean>5710409107563</ean>
        <stock_local>0</stock_local>
        <stock_supplier_fast>629</stock_supplier_fast>
        <stock_supplier_slow>0</stock_supplier_slow>
        <total_stock>629</total_stock>
    </product>
    <product>
        <kodas>4310</kodas>
        <ean>5710409108713</ean>
        <stock_local>0</stock_local>
        <stock_supplier_fast>698</stock_supplier_fast>
        <stock_supplier_slow>0</stock_supplier_slow>
        <total_stock>698</total_stock>
    </product>
    <product>
        <kodas>4315</kodas>
        <ean>5710409108799</ean>
        <stock_local>0</stock_local>
        <stock_supplier_fast>78</stock_supplier_fast>
        <stock_supplier_slow>0</stock_supplier_slow>
        <total_stock>78</total_stock>
    </product>
    <product>
        <kodas>4322</kodas>
        <ean>5710409109994</ean>
        <stock_local>0</stock_local>
        <stock_supplier_fast>130</stock_supplier_fast>
        <stock_supplier_slow>0</stock_supplier_slow>
        <total_stock>130</total_stock>
    </product>
    <product>
        <kodas>4323</kodas>
        <ean>5710409110006</ean>
        <stock_local>0</stock_local>
        <stock_supplier_fast>170</stock_supplier_fast>
        <stock_supplier_slow>0</stock_supplier_slow>
        <total_stock>170</total_stock>
    </product>
    <product>
        <kodas>4324</kodas>
        <ean>5710409110013</ean>
        <stock_local>0</stock_local>
        <stock_supplier_fast>449</stock_supplier_fast>
        <stock_supplier_slow>0</stock_supplier_slow>
        <total_stock>449</total_stock>
    </product>
    <product>
        <kodas>4325</kodas>
        <ean>5710409110020</ean>
        <stock_local>0</stock_local>
        <stock_supplier_fast>68</stock_supplier_fast>
        <stock_supplier_slow>0</stock_supplier_slow>
        <total_stock>68</total_stock>
    </product>
    <product>
        <kodas>4326</kodas>
        <ean>5710409110037</ean>
        <stock_local>0</stock_local>
        <stock_supplier_fast>101</stock_supplier_fast>
        <stock_supplier_slow>0</stock_supplier_slow>
        <total_stock>101</total_stock>
    </product>
    <product>
        <kodas>4327</kodas>
        <ean>5710409110044</ean>
        <stock_local>0</stock_local>
        <stock_supplier_fast>120</stock_supplier_fast>
        <stock_supplier_slow>0</stock_supplier_slow>
        <total_stock>120</total_stock>
    </product>
    <product>
        <kodas>4329</kodas>
        <ean>5710409110068</ean>
        <stock_local>0</stock_local>
        <stock_supplier_fast>77</stock_supplier_fast>
        <stock_supplier_slow>0</stock_supplier_slow>
        <total_stock>77</total_stock>
    </product>
    <product>
        <kodas>4390</kodas>
        <ean>5710409112277</ean>
        <stock_local>0</stock_local>
        <stock_supplier_fast>31</stock_supplier_fast>
        <stock_supplier_slow>0</stock_supplier_slow>
        <total_stock>31</total_stock>
    </product>
    <product>
        <kodas>4391</kodas>
        <ean>5710409112284</ean>
        <stock_local>0</stock_local>
        <stock_supplier_fast>32</stock_supplier_fast>
        <stock_supplier_slow>0</stock_supplier_slow>
        <total_stock>32</total_stock>
    </product>
    <product>
        <kodas>4392</kodas>
        <ean>5710409112291</ean>
        <stock_local>0</stock_local>
        <stock_supplier_fast>31</stock_supplier_fast>
        <stock_supplier_slow>0</stock_supplier_slow>
        <total_stock>31</total_stock>
    </product>
    <product>
        <kodas>4393</kodas>
        <ean>5710409112307</ean>
        <stock_local>0</stock_local>
        <stock_supplier_fast>31</stock_supplier_fast>
        <stock_supplier_slow>0</stock_supplier_slow>
        <total_stock>31</total_stock>
    </product>
    <product>
        <kodas>4397</kodas>
        <ean>5710409202282</ean>
        <stock_local>0</stock_local>
        <stock_supplier_fast>14</stock_supplier_fast>
        <stock_supplier_slow>0</stock_supplier_slow>
        <total_stock>14</total_stock>
    </product>
    <product>
        <kodas>4398</kodas>
        <ean>5710409202299</ean>
        <stock_local>0</stock_local>
        <stock_supplier_fast>32</stock_supplier_fast>
        <stock_supplier_slow>0</stock_supplier_slow>
        <total_stock>32</total_stock>
    </product>
    <product>
        <kodas>4400</kodas>
        <ean>5710409202312</ean>
        <stock_local>0</stock_local>
        <stock_supplier_fast>35</stock_supplier_fast>
        <stock_supplier_slow>0</stock_supplier_slow>
        <total_stock>35</total_stock>
    </product>
    <product>
        <kodas>4410</kodas>
        <ean>5710409113120</ean>
        <stock_local>0</stock_local>
        <stock_supplier_fast>2</stock_supplier_fast>
        <stock_supplier_slow>0</stock_supplier_slow>
        <total_stock>2</total_stock>
    </product>
    <product>
        <kodas>4411</kodas>
        <ean>5710409113168</ean>
        <stock_local>0</stock_local>
        <stock_supplier_fast>33</stock_supplier_fast>
        <stock_supplier_slow>0</stock_supplier_slow>
        <total_stock>33</total_stock>
    </product>
    <product>
        <kodas>50P6136</kodas>
        <ean>5055166361361</ean>
        <stock_local>0</stock_local>
        <stock_supplier_fast>18</stock_supplier_fast>
        <stock_supplier_slow>0</stock_supplier_slow>
        <total_stock>18</total_stock>
    </product>
    <product>
        <kodas>52P6270</kodas>
        <ean>5055166362702</ean>
        <stock_local>0</stock_local>
        <stock_supplier_fast>21</stock_supplier_fast>
        <stock_supplier_slow>0</stock_supplier_slow>
        <total_stock>21</total_stock>
    </product>
    <product>
        <kodas>52P6271</kodas>
        <ean>5055166362719</ean>
        <stock_local>0</stock_local>
        <stock_supplier_fast>21</stock_supplier_fast>
        <stock_supplier_slow>0</stock_supplier_slow>
        <total_stock>21</total_stock>
    </product>
    <product>
        <kodas>52P6273</kodas>
        <ean>5055166362733</ean>
        <stock_local>0</stock_local>
        <stock_supplier_fast>23</stock_supplier_fast>
        <stock_supplier_slow>0</stock_supplier_slow>
        <total_stock>23</total_stock>
    </product>
    <product>
        <kodas>52P6277</kodas>
        <ean>5055166362771</ean>
        <stock_local>0</stock_local>
        <stock_supplier_fast>19</stock_supplier_fast>
        <stock_supplier_slow>0</stock_supplier_slow>
        <total_stock>19</total_stock>
    </product>
    <product>
        <kodas>52P6278</kodas>
        <ean>5055166362788</ean>
        <stock_local>0</stock_local>
        <stock_supplier_fast>19</stock_supplier_fast>
        <stock_supplier_slow>0</stock_supplier_slow>
        <total_stock>19</total_stock>
    </product>
    <product>
        <kodas>52P6279</kodas>
        <ean>5055166362795</ean>
        <stock_local>0</stock_local>
        <stock_supplier_fast>22</stock_supplier_fast>
        <stock_supplier_slow>0</stock_supplier_slow>
        <total_stock>22</total_stock>
    </product>
    <product>
        <kodas>52P6282</kodas>
        <ean>5055166362825</ean>
        <stock_local>0</stock_local>
        <stock_supplier_fast>7</stock_supplier_fast>
        <stock_supplier_slow>0</stock_supplier_slow>
        <total_stock>7</total_stock>
    </product>
    <product>
        <kodas>52P6283</kodas>
        <ean>5055166362832</ean>
        <stock_local>0</stock_local>
        <stock_supplier_fast>7</stock_supplier_fast>
        <stock_supplier_slow>0</stock_supplier_slow>
        <total_stock>7</total_stock>
    </product>
    <product>
        <kodas>52P6285</kodas>
        <ean>5055166362856</ean>
        <stock_local>0</stock_local>
        <stock_supplier_fast>2</stock_supplier_fast>
        <stock_supplier_slow>0</stock_supplier_slow>
        <total_stock>2</total_stock>
    </product>
    <product>
        <kodas>52P6289</kodas>
        <ean>5055166362894</ean>
        <stock_local>0</stock_local>
        <stock_supplier_fast>3</stock_supplier_fast>
        <stock_supplier_slow>0</stock_supplier_slow>
        <total_stock>3</total_stock>
    </product>
    <product>
        <kodas>52P6290</kodas>
        <ean>5055166362900</ean>
        <stock_local>0</stock_local>
        <stock_supplier_fast>3</stock_supplier_fast>
        <stock_supplier_slow>0</stock_supplier_slow>
        <total_stock>3</total_stock>
    </product>
    <product>
        <kodas>52P6291</kodas>
        <ean>5055166362917</ean>
        <stock_local>0</stock_local>
        <stock_supplier_fast>2</stock_supplier_fast>
        <stock_supplier_slow>0</stock_supplier_slow>
        <total_stock>2</total_stock>
    </product>
    <product>
        <kodas>52P6298B</kodas>
        <ean>5055166362986</ean>
        <stock_local>0</stock_local>
        <stock_supplier_fast>10</stock_supplier_fast>
        <stock_supplier_slow>0</stock_supplier_slow>
        <total_stock>10</total_stock>
    </product>
    <product>
        <kodas>52P6298C</kodas>
        <ean>5055166362986</ean>
        <stock_local>0</stock_local>
        <stock_supplier_fast>2</stock_supplier_fast>
        <stock_supplier_slow>0</stock_supplier_slow>
        <total_stock>2</total_stock>
    </product>
    <product>
        <kodas>52P6316B</kodas>
        <ean>5055166363167</ean>
        <stock_local>0</stock_local>
        <stock_supplier_fast>6</stock_supplier_fast>
        <stock_supplier_slow>0</stock_supplier_slow>
        <total_stock>6</total_stock>
    </product>
    <product>
        <kodas>52P6320A</kodas>
        <ean>5055166363204</ean>
        <stock_local>0</stock_local>
        <stock_supplier_fast>9</stock_supplier_fast>
        <stock_supplier_slow>0</stock_supplier_slow>
        <total_stock>9</total_stock>
    </product>
    <product>
        <kodas>52P6320B</kodas>
        <ean>5055166363204</ean>
        <stock_local>0</stock_local>
        <stock_supplier_fast>18</stock_supplier_fast>
        <stock_supplier_slow>0</stock_supplier_slow>
        <total_stock>18</total_stock>
    </product>
    <product>
        <kodas>52P6320C</kodas>
        <ean>5055166363204</ean>
        <stock_local>0</stock_local>
        <stock_supplier_fast>8</stock_supplier_fast>
        <stock_supplier_slow>0</stock_supplier_slow>
        <total_stock>8</total_stock>
    </product>
    <product>
        <kodas>52P6328A</kodas>
        <ean>5055166363280</ean>
        <stock_local>0</stock_local>
        <stock_supplier_fast>19</stock_supplier_fast>
        <stock_supplier_slow>0</stock_supplier_slow>
        <total_stock>19</total_stock>
    </product>
    <product>
        <kodas>52P6328B</kodas>
        <ean>5055166363280</ean>
        <stock_local>0</stock_local>
        <stock_supplier_fast>9</stock_supplier_fast>
        <stock_supplier_slow>0</stock_supplier_slow>
        <total_stock>9</total_stock>
    </product>
    <product>
        <kodas>52P6328D</kodas>
        <ean>5055166363280</ean>
        <stock_local>0</stock_local>
        <stock_supplier_fast>19</stock_supplier_fast>
        <stock_supplier_slow>0</stock_supplier_slow>
        <total_stock>19</total_stock>
    </product>
    <product>
        <kodas>52P6330A</kodas>
        <ean>5055166363303</ean>
        <stock_local>0</stock_local>
        <stock_supplier_fast>12</stock_supplier_fast>
        <stock_supplier_slow>0</stock_supplier_slow>
        <total_stock>12</total_stock>
    </product>
    <product>
        <kodas>52P6330B</kodas>
        <ean>5055166363303</ean>
        <stock_local>0</stock_local>
        <stock_supplier_fast>13</stock_supplier_fast>
        <stock_supplier_slow>0</stock_supplier_slow>
        <total_stock>13</total_stock>
    </product>
    <product>
        <kodas>52P6330D</kodas>
        <ean>5055166363303</ean>
        <stock_local>0</stock_local>
        <stock_supplier_fast>12</stock_supplier_fast>
        <stock_supplier_slow>0</stock_supplier_slow>
        <total_stock>12</total_stock>
    </product>
    <product>
        <kodas>52P6330E</kodas>
        <ean>5055166363303</ean>
        <stock_local>0</stock_local>
        <stock_supplier_fast>12</stock_supplier_fast>
        <stock_supplier_slow>0</stock_supplier_slow>
        <total_stock>12</total_stock>
    </product>
    <product>
        <kodas>52P6330F</kodas>
        <ean>5055166363303</ean>
        <stock_local>0</stock_local>
        <stock_supplier_fast>7</stock_supplier_fast>
        <stock_supplier_slow>0</stock_supplier_slow>
        <total_stock>7</total_stock>
    </product>
    <product>
        <kodas>52P6337</kodas>
        <ean>5055166363372</ean>
        <stock_local>0</stock_local>
        <stock_supplier_fast>53</stock_supplier_fast>
        <stock_supplier_slow>0</stock_supplier_slow>
        <total_stock>53</total_stock>
    </product>
    <product>
        <kodas>52P6339</kodas>
        <ean>5055166363396</ean>
        <stock_local>0</stock_local>
        <stock_supplier_fast>58</stock_supplier_fast>
        <stock_supplier_slow>0</stock_supplier_slow>
        <total_stock>58</total_stock>
    </product>
    <product>
        <kodas>52P6342A</kodas>
        <ean>5055166363426</ean>
        <stock_local>0</stock_local>
        <stock_supplier_fast>2</stock_supplier_fast>
        <stock_supplier_slow>0</stock_supplier_slow>
        <total_stock>2</total_stock>
    </product>
    <product>
        <kodas>52P6342C</kodas>
        <ean>5055166363426</ean>
        <stock_local>0</stock_local>
        <stock_supplier_fast>7</stock_supplier_fast>
        <stock_supplier_slow>0</stock_supplier_slow>
        <total_stock>7</total_stock>
    </product>
    <product>
        <kodas>52P6342D</kodas>
        <ean>5055166363426</ean>
        <stock_local>0</stock_local>
        <stock_supplier_fast>8</stock_supplier_fast>
        <stock_supplier_slow>0</stock_supplier_slow>
        <total_stock>8</total_stock>
    </product>
    <product>
        <kodas>52P6347</kodas>
        <ean>5055166363471</ean>
        <stock_local>0</stock_local>
        <stock_supplier_fast>35</stock_supplier_fast>
        <stock_supplier_slow>0</stock_supplier_slow>
        <total_stock>35</total_stock>
    </product>
    <product>
        <kodas>52P6352</kodas>
        <ean>5055166363525</ean>
        <stock_local>0</stock_local>
        <stock_supplier_fast>5</stock_supplier_fast>
        <stock_supplier_slow>0</stock_supplier_slow>
        <total_stock>5</total_stock>
    </product>
    <product>
        <kodas>52P6353</kodas>
        <ean>5055166363532</ean>
        <stock_local>0</stock_local>
        <stock_supplier_fast>38</stock_supplier_fast>
        <stock_supplier_slow>0</stock_supplier_slow>
        <total_stock>38</total_stock>
    </product>
    <product>
        <kodas>57474</kodas>
        <ean>5707167945230</ean>
        <stock_local>0</stock_local>
        <stock_supplier_fast>344</stock_supplier_fast>
        <stock_supplier_slow>0</stock_supplier_slow>
        <total_stock>344</total_stock>
    </product>
    <product>
        <kodas>5902746</kodas>
        <ean>4052396088045</ean>
        <stock_local>0</stock_local>
        <stock_supplier_fast>0</stock_supplier_fast>
        <stock_supplier_slow>15</stock_supplier_slow>
        <total_stock>15</total_stock>
    </product>
    <product>
        <kodas>5902816</kodas>
        <ean>5901691870222</ean>
        <stock_local>0</stock_local>
        <stock_supplier_fast>0</stock_supplier_fast>
        <stock_supplier_slow>1</stock_supplier_slow>
        <total_stock>1</total_stock>
    </product>
    <product>
        <kodas>5903221</kodas>
        <ean>5905489408017</ean>
        <stock_local>0</stock_local>
        <stock_supplier_fast>0</stock_supplier_fast>
        <stock_supplier_slow>15</stock_supplier_slow>
        <total_stock>15</total_stock>
    </product>
    <product>
        <kodas>5903222</kodas>
        <ean>5905489408031</ean>
        <stock_local>0</stock_local>
        <stock_supplier_fast>0</stock_supplier_fast>
        <stock_supplier_slow>15</stock_supplier_slow>
        <total_stock>15</total_stock>
    </product>
    <product>
        <kodas>5903522</kodas>
        <ean>5904165684271</ean>
        <stock_local>0</stock_local>
        <stock_supplier_fast>0</stock_supplier_fast>
        <stock_supplier_slow>1</stock_supplier_slow>
        <total_stock>1</total_stock>
    </product>
    <product>
        <kodas>5903524</kodas>
        <ean>5904165684288</ean>
        <stock_local>0</stock_local>
        <stock_supplier_fast>0</stock_supplier_fast>
        <stock_supplier_slow>1</stock_supplier_slow>
        <total_stock>1</total_stock>
    </product>
    <product>
        <kodas>5903820</kodas>
        <ean>4052396093148</ean>
        <stock_local>0</stock_local>
        <stock_supplier_fast>0</stock_supplier_fast>
        <stock_supplier_slow>5</stock_supplier_slow>
        <total_stock>5</total_stock>
    </product>
    <product>
        <kodas>5904298</kodas>
        <ean>5903407353531</ean>
        <stock_local>0</stock_local>
        <stock_supplier_fast>0</stock_supplier_fast>
        <stock_supplier_slow>1</stock_supplier_slow>
        <total_stock>1</total_stock>
    </product>
    <product>
        <kodas>5904842</kodas>
        <ean>4052396092981</ean>
        <stock_local>0</stock_local>
        <stock_supplier_fast>0</stock_supplier_fast>
        <stock_supplier_slow>1</stock_supplier_slow>
        <total_stock>1</total_stock>
    </product>
    <product>
        <kodas>5904843</kodas>
        <ean>4052396092998</ean>
        <stock_local>0</stock_local>
        <stock_supplier_fast>0</stock_supplier_fast>
        <stock_supplier_slow>5</stock_supplier_slow>
        <total_stock>5</total_stock>
    </product>
    <product>
        <kodas>5905073</kodas>
        <ean>5905489408260</ean>
        <stock_local>0</stock_local>
        <stock_supplier_fast>0</stock_supplier_fast>
        <stock_supplier_slow>15</stock_supplier_slow>
        <total_stock>15</total_stock>
    </product>
    <product>
        <kodas>5905081</kodas>
        <ean>5900694411029</ean>
        <stock_local>0</stock_local>
        <stock_supplier_fast>0</stock_supplier_fast>
        <stock_supplier_slow>0</stock_supplier_slow>
        <total_stock>0</total_stock>
    </product>
    <product>
        <kodas>5905101</kodas>
        <ean>5900694411227</ean>
        <stock_local>0</stock_local>
        <stock_supplier_fast>0</stock_supplier_fast>
        <stock_supplier_slow>0</stock_supplier_slow>
        <total_stock>0</total_stock>
    </product>
    <product>
        <kodas>5905114</kodas>
        <ean>5900694411432</ean>
        <stock_local>0</stock_local>
        <stock_supplier_fast>0</stock_supplier_fast>
        <stock_supplier_slow>0</stock_supplier_slow>
        <total_stock>0</total_stock>
    </product>
    <product>
        <kodas>5905834</kodas>
        <ean>5907672341958</ean>
        <stock_local>0</stock_local>
        <stock_supplier_fast>0</stock_supplier_fast>
        <stock_supplier_slow>1</stock_supplier_slow>
        <total_stock>1</total_stock>
    </product>
    <product>
        <kodas>5906300</kodas>
        <ean>5900694431409</ean>
        <stock_local>0</stock_local>
        <stock_supplier_fast>0</stock_supplier_fast>
        <stock_supplier_slow>0</stock_supplier_slow>
        <total_stock>0</total_stock>
    </product>
    <product>
        <kodas>5906302</kodas>
        <ean>5900694433007</ean>
        <stock_local>0</stock_local>
        <stock_supplier_fast>0</stock_supplier_fast>
        <stock_supplier_slow>0</stock_supplier_slow>
        <total_stock>0</total_stock>
    </product>
    <product>
        <kodas>5906639</kodas>
        <ean>5904165685360</ean>
        <stock_local>0</stock_local>
        <stock_supplier_fast>0</stock_supplier_fast>
        <stock_supplier_slow>0</stock_supplier_slow>
        <total_stock>0</total_stock>
    </product>
    <product>
        <kodas>5906641</kodas>
        <ean>5904165685384</ean>
        <stock_local>0</stock_local>
        <stock_supplier_fast>0</stock_supplier_fast>
        <stock_supplier_slow>1</stock_supplier_slow>
        <total_stock>1</total_stock>
    </product>
    <product>
        <kodas>5906642</kodas>
        <ean>5904165685391</ean>
        <stock_local>0</stock_local>
        <stock_supplier_fast>0</stock_supplier_fast>
        <stock_supplier_slow>1</stock_supplier_slow>
        <total_stock>1</total_stock>
    </product>
    <product>
        <kodas>5907192</kodas>
        <ean>5907644005734</ean>
        <stock_local>0</stock_local>
        <stock_supplier_fast>0</stock_supplier_fast>
        <stock_supplier_slow>0</stock_supplier_slow>
        <total_stock>0</total_stock>
    </product>
    <product>
        <kodas>5908020</kodas>
        <ean>5905204312711</ean>
        <stock_local>0</stock_local>
        <stock_supplier_fast>0</stock_supplier_fast>
        <stock_supplier_slow>0</stock_supplier_slow>
        <total_stock>0</total_stock>
    </product>
    <product>
        <kodas>5908407</kodas>
        <ean>5904165687449</ean>
        <stock_local>0</stock_local>
        <stock_supplier_fast>0</stock_supplier_fast>
        <stock_supplier_slow>1</stock_supplier_slow>
        <total_stock>1</total_stock>
    </product>
    <product>
        <kodas>5908757</kodas>
        <ean>5901691885707</ean>
        <stock_local>0</stock_local>
        <stock_supplier_fast>0</stock_supplier_fast>
        <stock_supplier_slow>5</stock_supplier_slow>
        <total_stock>5</total_stock>
    </product>
    <product>
        <kodas>5910084</kodas>
        <ean>5903407163345</ean>
        <stock_local>0</stock_local>
        <stock_supplier_fast>0</stock_supplier_fast>
        <stock_supplier_slow>5</stock_supplier_slow>
        <total_stock>5</total_stock>
    </product>
    <product>
        <kodas>5910238</kodas>
        <ean>5907672345345</ean>
        <stock_local>0</stock_local>
        <stock_supplier_fast>0</stock_supplier_fast>
        <stock_supplier_slow>1</stock_supplier_slow>
        <total_stock>1</total_stock>
    </product>
    <product>
        <kodas>5910242</kodas>
        <ean>5907672345338</ean>
        <stock_local>0</stock_local>
        <stock_supplier_fast>0</stock_supplier_fast>
        <stock_supplier_slow>5</stock_supplier_slow>
        <total_stock>5</total_stock>
    </product>
    <product>
        <kodas>5910247</kodas>
        <ean>5901912245624</ean>
        <stock_local>0</stock_local>
        <stock_supplier_fast>0</stock_supplier_fast>
        <stock_supplier_slow>0</stock_supplier_slow>
        <total_stock>0</total_stock>
    </product>
    <product>
        <kodas>5910786</kodas>
        <ean>5907672345482</ean>
        <stock_local>0</stock_local>
        <stock_supplier_fast>0</stock_supplier_fast>
        <stock_supplier_slow>5</stock_supplier_slow>
        <total_stock>5</total_stock>
    </product>
    <product>
        <kodas>5910864</kodas>
        <ean>4052396112641</ean>
        <stock_local>0</stock_local>
        <stock_supplier_fast>0</stock_supplier_fast>
        <stock_supplier_slow>5</stock_supplier_slow>
        <total_stock>5</total_stock>
    </product>
    <product>
        <kodas>5911040</kodas>
        <ean>9353965008446</ean>
        <stock_local>0</stock_local>
        <stock_supplier_fast>0</stock_supplier_fast>
        <stock_supplier_slow>0</stock_supplier_slow>
        <total_stock>0</total_stock>
    </product>
    <product>
        <kodas>5911167</kodas>
        <ean>5901435416976</ean>
        <stock_local>0</stock_local>
        <stock_supplier_fast>0</stock_supplier_fast>
        <stock_supplier_slow>0</stock_supplier_slow>
        <total_stock>0</total_stock>
    </product>
    <product>
        <kodas>5911168</kodas>
        <ean>5901435416983</ean>
        <stock_local>0</stock_local>
        <stock_supplier_fast>0</stock_supplier_fast>
        <stock_supplier_slow>0</stock_supplier_slow>
        <total_stock>0</total_stock>
    </product>
    <product>
        <kodas>5911169</kodas>
        <ean>5901435416990</ean>
        <stock_local>0</stock_local>
        <stock_supplier_fast>0</stock_supplier_fast>
        <stock_supplier_slow>1</stock_supplier_slow>
        <total_stock>1</total_stock>
    </product>
    <product>
        <kodas>5911294</kodas>
        <ean>5903407165332</ean>
        <stock_local>0</stock_local>
        <stock_supplier_fast>0</stock_supplier_fast>
        <stock_supplier_slow>0</stock_supplier_slow>
        <total_stock>0</total_stock>
    </product>
    <product>
        <kodas>59114518</kodas>
        <ean>5900694222403</ean>
        <stock_local>0</stock_local>
        <stock_supplier_fast>0</stock_supplier_fast>
        <stock_supplier_slow>0</stock_supplier_slow>
        <total_stock>0</total_stock>
    </product>
    <product>
        <kodas>59114585</kodas>
        <stock_local>0</stock_local>
        <stock_supplier_fast>0</stock_supplier_fast>
        <stock_supplier_slow>0</stock_supplier_slow>
        <total_stock>0</total_stock>
    </product>
    <product>
        <kodas>59114586</kodas>
        <stock_local>0</stock_local>
        <stock_supplier_fast>0</stock_supplier_fast>
        <stock_supplier_slow>0</stock_supplier_slow>
        <total_stock>0</total_stock>
    </product>
    <product>
        <kodas>59114587</kodas>
        <stock_local>0</stock_local>
        <stock_supplier_fast>0</stock_supplier_fast>
        <stock_supplier_slow>0</stock_supplier_slow>
        <total_stock>0</total_stock>
    </product>
    <product>
        <kodas>59114588</kodas>
        <stock_local>0</stock_local>
        <stock_supplier_fast>0</stock_supplier_fast>
        <stock_supplier_slow>0</stock_supplier_slow>
        <total_stock>0</total_stock>
    </product>
    <product>
        <kodas>59114589</kodas>
        <stock_local>0</stock_local>
        <stock_supplier_fast>0</stock_supplier_fast>
        <stock_supplier_slow>0</stock_supplier_slow>
        <total_stock>0</total_stock>
    </product>
    <product>
        <kodas>59114590</kodas>
        <ean>5904722258754</ean>
        <stock_local>0</stock_local>
        <stock_supplier_fast>0</stock_supplier_fast>
        <stock_supplier_slow>0</stock_supplier_slow>
        <total_stock>0</total_stock>
    </product>
    <product>
        <kodas>59114591</kodas>
        <ean>5904722259539</ean>
        <stock_local>0</stock_local>
        <stock_supplier_fast>0</stock_supplier_fast>
        <stock_supplier_slow>0</stock_supplier_slow>
        <total_stock>0</total_stock>
    </product>
    <product>
        <kodas>5911755</kodas>
        <ean>5904754608299</ean>
        <stock_local>0</stock_local>
        <stock_supplier_fast>0</stock_supplier_fast>
        <stock_supplier_slow>5</stock_supplier_slow>
        <total_stock>5</total_stock>
    </product>
    <product>
        <kodas>5911985</kodas>
        <ean>5907001940067</ean>
        <stock_local>0</stock_local>
        <stock_supplier_fast>0</stock_supplier_fast>
        <stock_supplier_slow>1</stock_supplier_slow>
        <total_stock>1</total_stock>
    </product>
    <product>
        <kodas>5912195</kodas>
        <ean>5900511626032</ean>
        <stock_local>0</stock_local>
        <stock_supplier_fast>0</stock_supplier_fast>
        <stock_supplier_slow>5</stock_supplier_slow>
        <total_stock>5</total_stock>
    </product>
    <product>
        <kodas>5912196</kodas>
        <ean>5900511626049</ean>
        <stock_local>0</stock_local>
        <stock_supplier_fast>0</stock_supplier_fast>
        <stock_supplier_slow>5</stock_supplier_slow>
        <total_stock>5</total_stock>
    </product>
    <product>
        <kodas>5912197</kodas>
        <ean>5900511626056</ean>
        <stock_local>0</stock_local>
        <stock_supplier_fast>0</stock_supplier_fast>
        <stock_supplier_slow>5</stock_supplier_slow>
        <total_stock>5</total_stock>
    </product>
    <product>
        <kodas>5912198</kodas>
        <ean>5900511626063</ean>
        <stock_local>0</stock_local>
        <stock_supplier_fast>0</stock_supplier_fast>
        <stock_supplier_slow>5</stock_supplier_slow>
        <total_stock>5</total_stock>
    </product>
    <product>
        <kodas>5912480</kodas>
        <ean>5907090700382</ean>
        <stock_local>0</stock_local>
        <stock_supplier_fast>0</stock_supplier_fast>
        <stock_supplier_slow>5</stock_supplier_slow>
        <total_stock>5</total_stock>
    </product>
    <product>
        <kodas>5912612</kodas>
        <ean>5901691802834</ean>
        <stock_local>0</stock_local>
        <stock_supplier_fast>0</stock_supplier_fast>
        <stock_supplier_slow>5</stock_supplier_slow>
        <total_stock>5</total_stock>
    </product>
    <product>
        <kodas>5912644</kodas>
        <ean>5903407172606</ean>
        <stock_local>0</stock_local>
        <stock_supplier_fast>0</stock_supplier_fast>
        <stock_supplier_slow>0</stock_supplier_slow>
        <total_stock>0</total_stock>
    </product>
    <product>
        <kodas>5912776</kodas>
        <stock_local>0</stock_local>
        <stock_supplier_fast>0</stock_supplier_fast>
        <stock_supplier_slow>0</stock_supplier_slow>
        <total_stock>0</total_stock>
    </product>
    <product>
        <kodas>5913024</kodas>
        <ean>5907672346441</ean>
        <stock_local>0</stock_local>
        <stock_supplier_fast>0</stock_supplier_fast>
        <stock_supplier_slow>1</stock_supplier_slow>
        <total_stock>1</total_stock>
    </product>
    <product>
        <kodas>5913026</kodas>
        <ean>5907672346458</ean>
        <stock_local>0</stock_local>
        <stock_supplier_fast>0</stock_supplier_fast>
        <stock_supplier_slow>1</stock_supplier_slow>
        <total_stock>1</total_stock>
    </product>
    <product>
        <kodas>5913085</kodas>
        <ean>4052396093162</ean>
        <stock_local>0</stock_local>
        <stock_supplier_fast>0</stock_supplier_fast>
        <stock_supplier_slow>5</stock_supplier_slow>
        <total_stock>5</total_stock>
    </product>
    <product>
        <kodas>5913122</kodas>
        <ean>4052396127782</ean>
        <stock_local>0</stock_local>
        <stock_supplier_fast>0</stock_supplier_fast>
        <stock_supplier_slow>1</stock_supplier_slow>
        <total_stock>1</total_stock>
    </product>
    <product>
        <kodas>5913123</kodas>
        <ean>4052396127799</ean>
        <stock_local>0</stock_local>
        <stock_supplier_fast>0</stock_supplier_fast>
        <stock_supplier_slow>1</stock_supplier_slow>
        <total_stock>1</total_stock>
    </product>
    <product>
        <kodas>5913440</kodas>
        <ean>628123810193</ean>
        <stock_local>0</stock_local>
        <stock_supplier_fast>0</stock_supplier_fast>
        <stock_supplier_slow>0</stock_supplier_slow>
        <total_stock>0</total_stock>
    </product>
    <product>
        <kodas>5913613</kodas>
        <ean>5907644007059</ean>
        <stock_local>0</stock_local>
        <stock_supplier_fast>0</stock_supplier_fast>
        <stock_supplier_slow>5</stock_supplier_slow>
        <total_stock>5</total_stock>
    </product>
    <product>
        <kodas>5913617</kodas>
        <ean>5904356743770</ean>
        <stock_local>0</stock_local>
        <stock_supplier_fast>0</stock_supplier_fast>
        <stock_supplier_slow>1</stock_supplier_slow>
        <total_stock>1</total_stock>
    </product>
    <product>
        <kodas>5913968</kodas>
        <ean>5901761127485</ean>
        <stock_local>0</stock_local>
        <stock_supplier_fast>0</stock_supplier_fast>
        <stock_supplier_slow>1</stock_supplier_slow>
        <total_stock>1</total_stock>
    </product>
    <product>
        <kodas>5913970</kodas>
        <ean>5901761127461</ean>
        <stock_local>0</stock_local>
        <stock_supplier_fast>0</stock_supplier_fast>
        <stock_supplier_slow>0</stock_supplier_slow>
        <total_stock>0</total_stock>
    </product>
    <product>
        <kodas>5914143</kodas>
        <ean>4052396071757</ean>
        <stock_local>0</stock_local>
        <stock_supplier_fast>0</stock_supplier_fast>
        <stock_supplier_slow>5</stock_supplier_slow>
        <total_stock>5</total_stock>
    </product>
    <product>
        <kodas>5914382</kodas>
        <ean>5905450162382</ean>
        <stock_local>0</stock_local>
        <stock_supplier_fast>0</stock_supplier_fast>
        <stock_supplier_slow>0</stock_supplier_slow>
        <total_stock>0</total_stock>
    </product>
    <product>
        <kodas>5914537</kodas>
        <ean>5902963002969</ean>
        <stock_local>0</stock_local>
        <stock_supplier_fast>0</stock_supplier_fast>
        <stock_supplier_slow>5</stock_supplier_slow>
        <total_stock>5</total_stock>
    </product>
    <product>
        <kodas>5914539</kodas>
        <ean>5905489408932</ean>
        <stock_local>0</stock_local>
        <stock_supplier_fast>0</stock_supplier_fast>
        <stock_supplier_slow>15</stock_supplier_slow>
        <total_stock>15</total_stock>
    </product>
    <product>
        <kodas>5914540</kodas>
        <ean>5905489408956</ean>
        <stock_local>0</stock_local>
        <stock_supplier_fast>0</stock_supplier_fast>
        <stock_supplier_slow>15</stock_supplier_slow>
        <total_stock>15</total_stock>
    </product>
    <product>
        <kodas>5914621</kodas>
        <ean>4052396136173</ean>
        <stock_local>0</stock_local>
        <stock_supplier_fast>0</stock_supplier_fast>
        <stock_supplier_slow>1</stock_supplier_slow>
        <total_stock>1</total_stock>
    </product>
    <product>
        <kodas>5914716</kodas>
        <ean>5905489408925</ean>
        <stock_local>0</stock_local>
        <stock_supplier_fast>0</stock_supplier_fast>
        <stock_supplier_slow>15</stock_supplier_slow>
        <total_stock>15</total_stock>
    </product>
    <product>
        <kodas>5914737</kodas>
        <ean>5907150361805</ean>
        <stock_local>0</stock_local>
        <stock_supplier_fast>0</stock_supplier_fast>
        <stock_supplier_slow>1</stock_supplier_slow>
        <total_stock>1</total_stock>
    </product>
    <product>
        <kodas>620</kodas>
        <stock_local>0</stock_local>
        <stock_supplier_fast>0</stock_supplier_fast>
        <stock_supplier_slow>0</stock_supplier_slow>
        <total_stock>0</total_stock>
    </product>
    <product>
        <kodas>761535</kodas>
        <ean>5907644013005</ean>
        <stock_local>0</stock_local>
        <stock_supplier_fast>0</stock_supplier_fast>
        <stock_supplier_slow>1</stock_supplier_slow>
        <total_stock>1</total_stock>
    </product>
    <product>
        <kodas>761924</kodas>
        <ean>5905279336001</ean>
        <stock_local>0</stock_local>
        <stock_supplier_fast>0</stock_supplier_fast>
        <stock_supplier_slow>1</stock_supplier_slow>
        <total_stock>1</total_stock>
    </product>
    <product>
        <kodas>762788</kodas>
        <ean>5902963008084</ean>
        <stock_local>0</stock_local>
        <stock_supplier_fast>0</stock_supplier_fast>
        <stock_supplier_slow>15</stock_supplier_slow>
        <total_stock>15</total_stock>
    </product>
    <product>
        <kodas>767349</kodas>
        <ean>5900694778160</ean>
        <stock_local>0</stock_local>
        <stock_supplier_fast>0</stock_supplier_fast>
        <stock_supplier_slow>5</stock_supplier_slow>
        <total_stock>5</total_stock>
    </product>
    <product>
        <kodas>767954</kodas>
        <ean>5900694321045</ean>
        <stock_local>0</stock_local>
        <stock_supplier_fast>0</stock_supplier_fast>
        <stock_supplier_slow>0</stock_supplier_slow>
        <total_stock>0</total_stock>
    </product>
    <product>
        <kodas>767962</kodas>
        <ean>5900694321144</ean>
        <stock_local>0</stock_local>
        <stock_supplier_fast>0</stock_supplier_fast>
        <stock_supplier_slow>0</stock_supplier_slow>
        <total_stock>0</total_stock>
    </product>
    <product>
        <kodas>770973</kodas>
        <ean>5902963071095</ean>
        <stock_local>0</stock_local>
        <stock_supplier_fast>0</stock_supplier_fast>
        <stock_supplier_slow>15</stock_supplier_slow>
        <total_stock>15</total_stock>
    </product>
    <product>
        <kodas>771347</kodas>
        <ean>5902963009982</ean>
        <stock_local>0</stock_local>
        <stock_supplier_fast>0</stock_supplier_fast>
        <stock_supplier_slow>15</stock_supplier_slow>
        <total_stock>15</total_stock>
    </product>
    <product>
        <kodas>771765</kodas>
        <ean>5902963008152</ean>
        <stock_local>0</stock_local>
        <stock_supplier_fast>0</stock_supplier_fast>
        <stock_supplier_slow>15</stock_supplier_slow>
        <total_stock>15</total_stock>
    </product>
    <product>
        <kodas>771767</kodas>
        <ean>5902963010018</ean>
        <stock_local>0</stock_local>
        <stock_supplier_fast>0</stock_supplier_fast>
        <stock_supplier_slow>15</stock_supplier_slow>
        <total_stock>15</total_stock>
    </product>
    <product>
        <kodas>771769</kodas>
        <ean>5902963010292</ean>
        <stock_local>0</stock_local>
        <stock_supplier_fast>0</stock_supplier_fast>
        <stock_supplier_slow>15</stock_supplier_slow>
        <total_stock>15</total_stock>
    </product>
    <product>
        <kodas>771956</kodas>
        <ean>5902963071767</ean>
        <stock_local>0</stock_local>
        <stock_supplier_fast>0</stock_supplier_fast>
        <stock_supplier_slow>5</stock_supplier_slow>
        <total_stock>5</total_stock>
    </product>
    <product>
        <kodas>772381</kodas>
        <ean>5902963071880</ean>
        <stock_local>0</stock_local>
        <stock_supplier_fast>0</stock_supplier_fast>
        <stock_supplier_slow>5</stock_supplier_slow>
        <total_stock>5</total_stock>
    </product>
    <product>
        <kodas>772382</kodas>
        <ean>5902963071897</ean>
        <stock_local>0</stock_local>
        <stock_supplier_fast>0</stock_supplier_fast>
        <stock_supplier_slow>5</stock_supplier_slow>
        <total_stock>5</total_stock>
    </product>
    <product>
        <kodas>772383</kodas>
        <ean>5902963071859</ean>
        <stock_local>0</stock_local>
        <stock_supplier_fast>0</stock_supplier_fast>
        <stock_supplier_slow>15</stock_supplier_slow>
        <total_stock>15</total_stock>
    </product>
    <product>
        <kodas>772393</kodas>
        <ean>5902963071903</ean>
        <stock_local>0</stock_local>
        <stock_supplier_fast>0</stock_supplier_fast>
        <stock_supplier_slow>1</stock_supplier_slow>
        <total_stock>1</total_stock>
    </product>
    <product>
        <kodas>772404</kodas>
        <ean>5902963015709</ean>
        <stock_local>0</stock_local>
        <stock_supplier_fast>0</stock_supplier_fast>
        <stock_supplier_slow>15</stock_supplier_slow>
        <total_stock>15</total_stock>
    </product>
    <product>
        <kodas>772405</kodas>
        <ean>5902963015693</ean>
        <stock_local>0</stock_local>
        <stock_supplier_fast>0</stock_supplier_fast>
        <stock_supplier_slow>5</stock_supplier_slow>
        <total_stock>5</total_stock>
    </product>
    <product>
        <kodas>772406</kodas>
        <ean>5902963015730</ean>
        <stock_local>0</stock_local>
        <stock_supplier_fast>0</stock_supplier_fast>
        <stock_supplier_slow>15</stock_supplier_slow>
        <total_stock>15</total_stock>
    </product>
    <product>
        <kodas>772407</kodas>
        <ean>5902963015716</ean>
        <stock_local>0</stock_local>
        <stock_supplier_fast>0</stock_supplier_fast>
        <stock_supplier_slow>15</stock_supplier_slow>
        <total_stock>15</total_stock>
    </product>
    <product>
        <kodas>772414</kodas>
        <ean>5902963071989</ean>
        <stock_local>0</stock_local>
        <stock_supplier_fast>0</stock_supplier_fast>
        <stock_supplier_slow>15</stock_supplier_slow>
        <total_stock>15</total_stock>
    </product>
    <product>
        <kodas>772415</kodas>
        <ean>5902963071996</ean>
        <stock_local>0</stock_local>
        <stock_supplier_fast>0</stock_supplier_fast>
        <stock_supplier_slow>15</stock_supplier_slow>
        <total_stock>15</total_stock>
    </product>
    <product>
        <kodas>772419</kodas>
        <ean>5902963015020</ean>
        <stock_local>0</stock_local>
        <stock_supplier_fast>0</stock_supplier_fast>
        <stock_supplier_slow>15</stock_supplier_slow>
        <total_stock>15</total_stock>
    </product>
    <product>
        <kodas>772420</kodas>
        <ean>5902963015037</ean>
        <stock_local>0</stock_local>
        <stock_supplier_fast>0</stock_supplier_fast>
        <stock_supplier_slow>15</stock_supplier_slow>
        <total_stock>15</total_stock>
    </product>
    <product>
        <kodas>772421</kodas>
        <ean>5902963014993</ean>
        <stock_local>0</stock_local>
        <stock_supplier_fast>0</stock_supplier_fast>
        <stock_supplier_slow>15</stock_supplier_slow>
        <total_stock>15</total_stock>
    </product>
    <product>
        <kodas>772532</kodas>
        <ean>5907644004102</ean>
        <stock_local>0</stock_local>
        <stock_supplier_fast>0</stock_supplier_fast>
        <stock_supplier_slow>0</stock_supplier_slow>
        <total_stock>0</total_stock>
    </product>
    <product>
        <kodas>772625</kodas>
        <ean>5902963015327</ean>
        <stock_local>0</stock_local>
        <stock_supplier_fast>0</stock_supplier_fast>
        <stock_supplier_slow>1</stock_supplier_slow>
        <total_stock>1</total_stock>
    </product>
    <product>
        <kodas>772626</kodas>
        <ean>5902963015341</ean>
        <stock_local>0</stock_local>
        <stock_supplier_fast>0</stock_supplier_fast>
        <stock_supplier_slow>5</stock_supplier_slow>
        <total_stock>5</total_stock>
    </product>
    <product>
        <kodas>772627</kodas>
        <ean>5902963015310</ean>
        <stock_local>0</stock_local>
        <stock_supplier_fast>0</stock_supplier_fast>
        <stock_supplier_slow>5</stock_supplier_slow>
        <total_stock>5</total_stock>
    </product>
    <product>
        <kodas>772629</kodas>
        <ean>5902963015358</ean>
        <stock_local>0</stock_local>
        <stock_supplier_fast>0</stock_supplier_fast>
        <stock_supplier_slow>5</stock_supplier_slow>
        <total_stock>5</total_stock>
    </product>
    <product>
        <kodas>773654</kodas>
        <ean>5901435408780</ean>
        <stock_local>0</stock_local>
        <stock_supplier_fast>0</stock_supplier_fast>
        <stock_supplier_slow>0</stock_supplier_slow>
        <total_stock>0</total_stock>
    </product>
    <product>
        <kodas>773705</kodas>
        <ean>4052396044881</ean>
        <stock_local>0</stock_local>
        <stock_supplier_fast>0</stock_supplier_fast>
        <stock_supplier_slow>15</stock_supplier_slow>
        <total_stock>15</total_stock>
    </product>
    <product>
        <kodas>773773</kodas>
        <ean>5902963015945</ean>
        <stock_local>0</stock_local>
        <stock_supplier_fast>0</stock_supplier_fast>
        <stock_supplier_slow>1</stock_supplier_slow>
        <total_stock>1</total_stock>
    </product>
    <product>
        <kodas>775233</kodas>
        <ean>4052396044393</ean>
        <stock_local>0</stock_local>
        <stock_supplier_fast>0</stock_supplier_fast>
        <stock_supplier_slow>5</stock_supplier_slow>
        <total_stock>5</total_stock>
    </product>
    <product>
        <kodas>775234</kodas>
        <ean>4052396080575</ean>
        <stock_local>0</stock_local>
        <stock_supplier_fast>0</stock_supplier_fast>
        <stock_supplier_slow>5</stock_supplier_slow>
        <total_stock>5</total_stock>
    </product>
    <product>
        <kodas>775237</kodas>
        <ean>4052396044898</ean>
        <stock_local>0</stock_local>
        <stock_supplier_fast>0</stock_supplier_fast>
        <stock_supplier_slow>15</stock_supplier_slow>
        <total_stock>15</total_stock>
    </product>
    <product>
        <kodas>775238</kodas>
        <ean>4052396044874</ean>
        <stock_local>0</stock_local>
        <stock_supplier_fast>0</stock_supplier_fast>
        <stock_supplier_slow>5</stock_supplier_slow>
        <total_stock>5</total_stock>
    </product>
    <product>
        <kodas>775944</kodas>
        <ean>5901691813069</ean>
        <stock_local>0</stock_local>
        <stock_supplier_fast>0</stock_supplier_fast>
        <stock_supplier_slow>0</stock_supplier_slow>
        <total_stock>0</total_stock>
    </product>
    <product>
        <kodas>776187</kodas>
        <ean>5903407680637</ean>
        <stock_local>0</stock_local>
        <stock_supplier_fast>0</stock_supplier_fast>
        <stock_supplier_slow>5</stock_supplier_slow>
        <total_stock>5</total_stock>
    </product>
    <product>
        <kodas>776392</kodas>
        <ean>5902963011404</ean>
        <stock_local>0</stock_local>
        <stock_supplier_fast>0</stock_supplier_fast>
        <stock_supplier_slow>15</stock_supplier_slow>
        <total_stock>15</total_stock>
    </product>
    <product>
        <kodas>777114</kodas>
        <ean>5902963007087</ean>
        <stock_local>0</stock_local>
        <stock_supplier_fast>0</stock_supplier_fast>
        <stock_supplier_slow>15</stock_supplier_slow>
        <total_stock>15</total_stock>
    </product>
    <product>
        <kodas>777872</kodas>
        <ean>5903407742045</ean>
        <stock_local>0</stock_local>
        <stock_supplier_fast>0</stock_supplier_fast>
        <stock_supplier_slow>0</stock_supplier_slow>
        <total_stock>0</total_stock>
    </product>
    <product>
        <kodas>778837</kodas>
        <ean>5903407680835</ean>
        <stock_local>0</stock_local>
        <stock_supplier_fast>0</stock_supplier_fast>
        <stock_supplier_slow>1</stock_supplier_slow>
        <total_stock>1</total_stock>
    </product>
    <product>
        <kodas>779240</kodas>
        <ean>5902963001474</ean>
        <stock_local>0</stock_local>
        <stock_supplier_fast>0</stock_supplier_fast>
        <stock_supplier_slow>1</stock_supplier_slow>
        <total_stock>1</total_stock>
    </product>
    <product>
        <kodas>779241</kodas>
        <ean>5902963001443</ean>
        <stock_local>0</stock_local>
        <stock_supplier_fast>0</stock_supplier_fast>
        <stock_supplier_slow>1</stock_supplier_slow>
        <total_stock>1</total_stock>
    </product>
    <product>
        <kodas>779242</kodas>
        <ean>5902963001313</ean>
        <stock_local>0</stock_local>
        <stock_supplier_fast>0</stock_supplier_fast>
        <stock_supplier_slow>15</stock_supplier_slow>
        <total_stock>15</total_stock>
    </product>
    <product>
        <kodas>779254</kodas>
        <ean>5902963001306</ean>
        <stock_local>0</stock_local>
        <stock_supplier_fast>0</stock_supplier_fast>
        <stock_supplier_slow>5</stock_supplier_slow>
        <total_stock>5</total_stock>
    </product>
    <product>
        <kodas>779255</kodas>
        <ean>5902963001405</ean>
        <stock_local>0</stock_local>
        <stock_supplier_fast>0</stock_supplier_fast>
        <stock_supplier_slow>1</stock_supplier_slow>
        <total_stock>1</total_stock>
    </product>
    <product>
        <kodas>780867</kodas>
        <ean>5907672333076</ean>
        <stock_local>0</stock_local>
        <stock_supplier_fast>0</stock_supplier_fast>
        <stock_supplier_slow>1</stock_supplier_slow>
        <total_stock>1</total_stock>
    </product>
    <product>
        <kodas>781107</kodas>
        <ean>5903714260720</ean>
        <stock_local>0</stock_local>
        <stock_supplier_fast>0</stock_supplier_fast>
        <stock_supplier_slow>1</stock_supplier_slow>
        <total_stock>1</total_stock>
    </product>
    <product>
        <kodas>781567</kodas>
        <ean>4052396072839</ean>
        <stock_local>0</stock_local>
        <stock_supplier_fast>0</stock_supplier_fast>
        <stock_supplier_slow>1</stock_supplier_slow>
        <total_stock>1</total_stock>
    </product>
    <product>
        <kodas>781986</kodas>
        <ean>5904356927934</ean>
        <stock_local>0</stock_local>
        <stock_supplier_fast>0</stock_supplier_fast>
        <stock_supplier_slow>0</stock_supplier_slow>
        <total_stock>0</total_stock>
    </product>
    <product>
        <kodas>781987</kodas>
        <ean>5904356927903</ean>
        <stock_local>0</stock_local>
        <stock_supplier_fast>0</stock_supplier_fast>
        <stock_supplier_slow>0</stock_supplier_slow>
        <total_stock>0</total_stock>
    </product>
    <product>
        <kodas>781988</kodas>
        <ean>5904356927897</ean>
        <stock_local>0</stock_local>
        <stock_supplier_fast>0</stock_supplier_fast>
        <stock_supplier_slow>0</stock_supplier_slow>
        <total_stock>0</total_stock>
    </product>
    <product>
        <kodas>782524</kodas>
        <ean>8058664136018</ean>
        <stock_local>0</stock_local>
        <stock_supplier_fast>0</stock_supplier_fast>
        <stock_supplier_slow>1</stock_supplier_slow>
        <total_stock>1</total_stock>
    </product>
    <product>
        <kodas>782850</kodas>
        <ean>5902963001955</ean>
        <stock_local>0</stock_local>
        <stock_supplier_fast>0</stock_supplier_fast>
        <stock_supplier_slow>15</stock_supplier_slow>
        <total_stock>15</total_stock>
    </product>
    <product>
        <kodas>782851</kodas>
        <ean>5902963001948</ean>
        <stock_local>0</stock_local>
        <stock_supplier_fast>0</stock_supplier_fast>
        <stock_supplier_slow>15</stock_supplier_slow>
        <total_stock>15</total_stock>
    </product>
    <product>
        <kodas>782852</kodas>
        <ean>5902963001962</ean>
        <stock_local>0</stock_local>
        <stock_supplier_fast>0</stock_supplier_fast>
        <stock_supplier_slow>15</stock_supplier_slow>
        <total_stock>15</total_stock>
    </product>
    <product>
        <kodas>782853</kodas>
        <ean>5902963001931</ean>
        <stock_local>0</stock_local>
        <stock_supplier_fast>0</stock_supplier_fast>
        <stock_supplier_slow>15</stock_supplier_slow>
        <total_stock>15</total_stock>
    </product>
    <product>
        <kodas>782854</kodas>
        <ean>5902963001986</ean>
        <stock_local>0</stock_local>
        <stock_supplier_fast>0</stock_supplier_fast>
        <stock_supplier_slow>15</stock_supplier_slow>
        <total_stock>15</total_stock>
    </product>
    <product>
        <kodas>782855</kodas>
        <ean>5902963001979</ean>
        <stock_local>0</stock_local>
        <stock_supplier_fast>0</stock_supplier_fast>
        <stock_supplier_slow>15</stock_supplier_slow>
        <total_stock>15</total_stock>
    </product>
    <product>
        <kodas>783467</kodas>
        <ean>5904165680297</ean>
        <stock_local>0</stock_local>
        <stock_supplier_fast>0</stock_supplier_fast>
        <stock_supplier_slow>0</stock_supplier_slow>
        <total_stock>0</total_stock>
    </product>
    <product>
        <kodas>784456</kodas>
        <ean>5900694353169</ean>
        <stock_local>0</stock_local>
        <stock_supplier_fast>0</stock_supplier_fast>
        <stock_supplier_slow>1</stock_supplier_slow>
        <total_stock>1</total_stock>
    </product>
    <product>
        <kodas>786363</kodas>
        <ean>5902963002280</ean>
        <stock_local>0</stock_local>
        <stock_supplier_fast>0</stock_supplier_fast>
        <stock_supplier_slow>15</stock_supplier_slow>
        <total_stock>15</total_stock>
    </product>
    <product>
        <kodas>786364</kodas>
        <ean>5902963002273</ean>
        <stock_local>0</stock_local>
        <stock_supplier_fast>0</stock_supplier_fast>
        <stock_supplier_slow>15</stock_supplier_slow>
        <total_stock>15</total_stock>
    </product>
    <product>
        <kodas>786365</kodas>
        <ean>5902963002310</ean>
        <stock_local>0</stock_local>
        <stock_supplier_fast>0</stock_supplier_fast>
        <stock_supplier_slow>15</stock_supplier_slow>
        <total_stock>15</total_stock>
    </product>
    <product>
        <kodas>786640</kodas>
        <ean>5902963002761</ean>
        <stock_local>0</stock_local>
        <stock_supplier_fast>0</stock_supplier_fast>
        <stock_supplier_slow>5</stock_supplier_slow>
        <total_stock>5</total_stock>
    </product>
    <product>
        <kodas>786643</kodas>
        <ean>5902963002778</ean>
        <stock_local>0</stock_local>
        <stock_supplier_fast>0</stock_supplier_fast>
        <stock_supplier_slow>1</stock_supplier_slow>
        <total_stock>1</total_stock>
    </product>
    <product>
        <kodas>786664</kodas>
        <ean>5902963002884</ean>
        <stock_local>0</stock_local>
        <stock_supplier_fast>0</stock_supplier_fast>
        <stock_supplier_slow>15</stock_supplier_slow>
        <total_stock>15</total_stock>
    </product>
    <product>
        <kodas>786667</kodas>
        <ean>5902963002891</ean>
        <stock_local>0</stock_local>
        <stock_supplier_fast>0</stock_supplier_fast>
        <stock_supplier_slow>1</stock_supplier_slow>
        <total_stock>1</total_stock>
    </product>
    <product>
        <kodas>786668</kodas>
        <ean>5902963002921</ean>
        <stock_local>0</stock_local>
        <stock_supplier_fast>0</stock_supplier_fast>
        <stock_supplier_slow>5</stock_supplier_slow>
        <total_stock>5</total_stock>
    </product>
    <product>
        <kodas>786670</kodas>
        <ean>5902963002914</ean>
        <stock_local>0</stock_local>
        <stock_supplier_fast>0</stock_supplier_fast>
        <stock_supplier_slow>15</stock_supplier_slow>
        <total_stock>15</total_stock>
    </product>
    <product>
        <kodas>786671</kodas>
        <ean>5902963002938</ean>
        <stock_local>0</stock_local>
        <stock_supplier_fast>0</stock_supplier_fast>
        <stock_supplier_slow>5</stock_supplier_slow>
        <total_stock>5</total_stock>
    </product>
    <product>
        <kodas>786720</kodas>
        <ean>5903407022215</ean>
        <stock_local>0</stock_local>
        <stock_supplier_fast>0</stock_supplier_fast>
        <stock_supplier_slow>5</stock_supplier_slow>
        <total_stock>5</total_stock>
    </product>
    <product>
        <kodas>787373</kodas>
        <ean>5907644005147</ean>
        <stock_local>0</stock_local>
        <stock_supplier_fast>0</stock_supplier_fast>
        <stock_supplier_slow>0</stock_supplier_slow>
        <total_stock>0</total_stock>
    </product>
    <product>
        <kodas>787530</kodas>
        <ean>5904165682109</ean>
        <stock_local>0</stock_local>
        <stock_supplier_fast>0</stock_supplier_fast>
        <stock_supplier_slow>0</stock_supplier_slow>
        <total_stock>0</total_stock>
    </product>
    <product>
        <kodas>787532</kodas>
        <ean>5904165681843</ean>
        <stock_local>0</stock_local>
        <stock_supplier_fast>0</stock_supplier_fast>
        <stock_supplier_slow>1</stock_supplier_slow>
        <total_stock>1</total_stock>
    </product>
    <product>
        <kodas>787533</kodas>
        <ean>5904165681850</ean>
        <stock_local>0</stock_local>
        <stock_supplier_fast>0</stock_supplier_fast>
        <stock_supplier_slow>1</stock_supplier_slow>
        <total_stock>1</total_stock>
    </product>
    <product>
        <kodas>787845</kodas>
        <ean>5901691849679</ean>
        <stock_local>0</stock_local>
        <stock_supplier_fast>0</stock_supplier_fast>
        <stock_supplier_slow>1</stock_supplier_slow>
        <total_stock>1</total_stock>
    </product>
    <product>
        <kodas>787847</kodas>
        <ean>5901691849709</ean>
        <stock_local>0</stock_local>
        <stock_supplier_fast>0</stock_supplier_fast>
        <stock_supplier_slow>1</stock_supplier_slow>
        <total_stock>1</total_stock>
    </product>
    <product>
        <kodas>787988</kodas>
        <ean>6925783801818</ean>
        <stock_local>0</stock_local>
        <stock_supplier_fast>0</stock_supplier_fast>
        <stock_supplier_slow>0</stock_supplier_slow>
        <total_stock>0</total_stock>
    </product>
    <product>
        <kodas>787990</kodas>
        <ean>6925783801832</ean>
        <stock_local>0</stock_local>
        <stock_supplier_fast>0</stock_supplier_fast>
        <stock_supplier_slow>1</stock_supplier_slow>
        <total_stock>1</total_stock>
    </product>
    <product>
        <kodas>788006</kodas>
        <ean>6925783805809</ean>
        <stock_local>0</stock_local>
        <stock_supplier_fast>0</stock_supplier_fast>
        <stock_supplier_slow>0</stock_supplier_slow>
        <total_stock>0</total_stock>
    </product>
    <product>
        <kodas>78922</kodas>
        <ean>5707167199985</ean>
        <stock_local>0</stock_local>
        <stock_supplier_fast>146</stock_supplier_fast>
        <stock_supplier_slow>0</stock_supplier_slow>
        <total_stock>146</total_stock>
    </product>
    <product>
        <kodas>78923</kodas>
        <ean>5707167200018</ean>
        <stock_local>0</stock_local>
        <stock_supplier_fast>227</stock_supplier_fast>
        <stock_supplier_slow>0</stock_supplier_slow>
        <total_stock>227</total_stock>
    </product>
    <product>
        <kodas>78926</kodas>
        <ean>5707167200131</ean>
        <stock_local>0</stock_local>
        <stock_supplier_fast>141</stock_supplier_fast>
        <stock_supplier_slow>0</stock_supplier_slow>
        <total_stock>141</total_stock>
    </product>
    <product>
        <kodas>78927</kodas>
        <ean>5707167200100</ean>
        <stock_local>0</stock_local>
        <stock_supplier_fast>231</stock_supplier_fast>
        <stock_supplier_slow>0</stock_supplier_slow>
        <total_stock>231</total_stock>
    </product>
    <product>
        <kodas>789340</kodas>
        <ean>5907644011339</ean>
        <stock_local>0</stock_local>
        <stock_supplier_fast>0</stock_supplier_fast>
        <stock_supplier_slow>5</stock_supplier_slow>
        <total_stock>5</total_stock>
    </product>
    <product>
        <kodas>789833</kodas>
        <ean>5901691957916</ean>
        <stock_local>0</stock_local>
        <stock_supplier_fast>0</stock_supplier_fast>
        <stock_supplier_slow>1</stock_supplier_slow>
        <total_stock>1</total_stock>
    </product>
    <product>
        <kodas>790078</kodas>
        <ean>5900511023374</ean>
        <stock_local>0</stock_local>
        <stock_supplier_fast>0</stock_supplier_fast>
        <stock_supplier_slow>0</stock_supplier_slow>
        <total_stock>0</total_stock>
    </product>
    <product>
        <kodas>790694</kodas>
        <ean>5901811160370</ean>
        <stock_local>0</stock_local>
        <stock_supplier_fast>0</stock_supplier_fast>
        <stock_supplier_slow>0</stock_supplier_slow>
        <total_stock>0</total_stock>
    </product>
    <product>
        <kodas>790702</kodas>
        <ean>5901811132506</ean>
        <stock_local>0</stock_local>
        <stock_supplier_fast>0</stock_supplier_fast>
        <stock_supplier_slow>0</stock_supplier_slow>
        <total_stock>0</total_stock>
    </product>
    <product>
        <kodas>790830</kodas>
        <ean>4052396080599</ean>
        <stock_local>0</stock_local>
        <stock_supplier_fast>0</stock_supplier_fast>
        <stock_supplier_slow>15</stock_supplier_slow>
        <total_stock>15</total_stock>
    </product>
    <product>
        <kodas>790832</kodas>
        <ean>4052396080827</ean>
        <stock_local>0</stock_local>
        <stock_supplier_fast>0</stock_supplier_fast>
        <stock_supplier_slow>5</stock_supplier_slow>
        <total_stock>5</total_stock>
    </product>
    <product>
        <kodas>79109</kodas>
        <ean>5707167231661</ean>
        <stock_local>0</stock_local>
        <stock_supplier_fast>116</stock_supplier_fast>
        <stock_supplier_slow>0</stock_supplier_slow>
        <total_stock>116</total_stock>
    </product>
    <product>
        <kodas>791110</kodas>
        <ean>5907644000746</ean>
        <stock_local>0</stock_local>
        <stock_supplier_fast>0</stock_supplier_fast>
        <stock_supplier_slow>5</stock_supplier_slow>
        <total_stock>5</total_stock>
    </product>
    <product>
        <kodas>791255</kodas>
        <ean>661148247520</ean>
        <stock_local>0</stock_local>
        <stock_supplier_fast>0</stock_supplier_fast>
        <stock_supplier_slow>1</stock_supplier_slow>
        <total_stock>1</total_stock>
    </product>
    <product>
        <kodas>791265</kodas>
        <ean>4052396080803</ean>
        <stock_local>0</stock_local>
        <stock_supplier_fast>0</stock_supplier_fast>
        <stock_supplier_slow>15</stock_supplier_slow>
        <total_stock>15</total_stock>
    </product>
    <product>
        <kodas>791385</kodas>
        <ean>8058664144785</ean>
        <stock_local>0</stock_local>
        <stock_supplier_fast>0</stock_supplier_fast>
        <stock_supplier_slow>0</stock_supplier_slow>
        <total_stock>0</total_stock>
    </product>
    <product>
        <kodas>791456</kodas>
        <ean>6925783801382</ean>
        <stock_local>0</stock_local>
        <stock_supplier_fast>0</stock_supplier_fast>
        <stock_supplier_slow>1</stock_supplier_slow>
        <total_stock>1</total_stock>
    </product>
    <product>
        <kodas>8487</kodas>
        <ean>4052396092882</ean>
        <stock_local>0</stock_local>
        <stock_supplier_fast>0</stock_supplier_fast>
        <stock_supplier_slow>5</stock_supplier_slow>
        <total_stock>5</total_stock>
    </product>
    <product>
        <kodas>977548</kodas>
        <ean>5712854625876</ean>
        <stock_local>0</stock_local>
        <stock_supplier_fast>4</stock_supplier_fast>
        <stock_supplier_slow>0</stock_supplier_slow>
        <total_stock>4</total_stock>
    </product>
    <product>
        <kodas>B1330</kodas>
        <ean>6938242963026</ean>
        <stock_local>0</stock_local>
        <stock_supplier_fast>66</stock_supplier_fast>
        <stock_supplier_slow>0</stock_supplier_slow>
        <total_stock>66</total_stock>
    </product>
    <product>
        <kodas>BN81032</kodas>
        <ean>4019359810327</ean>
        <stock_local>0</stock_local>
        <stock_supplier_fast>50</stock_supplier_fast>
        <stock_supplier_slow>0</stock_supplier_slow>
        <total_stock>50</total_stock>
    </product>
    <product>
        <kodas>BN84163</kodas>
        <ean>4019359841635</ean>
        <stock_local>0</stock_local>
        <stock_supplier_fast>16</stock_supplier_fast>
        <stock_supplier_slow>0</stock_supplier_slow>
        <total_stock>16</total_stock>
    </product>
    <product>
        <kodas>BN88023</kodas>
        <ean>4019359880238</ean>
        <stock_local>0</stock_local>
        <stock_supplier_fast>23</stock_supplier_fast>
        <stock_supplier_slow>0</stock_supplier_slow>
        <total_stock>23</total_stock>
    </product>
    <product>
        <kodas>CT-O-00048-CR</kodas>
        <ean>850036293477</ean>
        <stock_local>3</stock_local>
        <stock_supplier_fast>0</stock_supplier_fast>
        <stock_supplier_slow>0</stock_supplier_slow>
        <total_stock>3</total_stock>
    </product>
    <product>
        <kodas>CT-P-00106-BR</kodas>
        <ean>850036293064</ean>
        <stock_local>1</stock_local>
        <stock_supplier_fast>0</stock_supplier_fast>
        <stock_supplier_slow>0</stock_supplier_slow>
        <total_stock>1</total_stock>
    </product>
    <product>
        <kodas>CT-P-00120-CR</kodas>
        <ean>850036293040</ean>
        <stock_local>0</stock_local>
        <stock_supplier_fast>0</stock_supplier_fast>
        <stock_supplier_slow>0</stock_supplier_slow>
        <total_stock>0</total_stock>
    </product>
    <product>
        <kodas>CT-P-00202-ME</kodas>
        <ean>850036293057</ean>
        <stock_local>0</stock_local>
        <stock_supplier_fast>0</stock_supplier_fast>
        <stock_supplier_slow>0</stock_supplier_slow>
        <total_stock>0</total_stock>
    </product>
    <product>
        <kodas>CT-R-00050-TR</kodas>
        <ean>850036293224</ean>
        <stock_local>1</stock_local>
        <stock_supplier_fast>0</stock_supplier_fast>
        <stock_supplier_slow>0</stock_supplier_slow>
        <total_stock>1</total_stock>
    </product>
    <product>
        <kodas>CT-R-00060-ST</kodas>
        <ean>850036293347</ean>
        <stock_local>1</stock_local>
        <stock_supplier_fast>0</stock_supplier_fast>
        <stock_supplier_slow>0</stock_supplier_slow>
        <total_stock>1</total_stock>
    </product>
    <product>
        <kodas>CT-R-00092-BR</kodas>
        <ean>850036293149</ean>
        <stock_local>1</stock_local>
        <stock_supplier_fast>0</stock_supplier_fast>
        <stock_supplier_slow>0</stock_supplier_slow>
        <total_stock>1</total_stock>
    </product>
    <product>
        <kodas>CT-R-00102-CR</kodas>
        <ean>850036293361</ean>
        <stock_local>5</stock_local>
        <stock_supplier_fast>0</stock_supplier_fast>
        <stock_supplier_slow>0</stock_supplier_slow>
        <total_stock>5</total_stock>
    </product>
    <product>
        <kodas>CT-R-00212-ME</kodas>
        <ean>850036293194</ean>
        <stock_local>1</stock_local>
        <stock_supplier_fast>0</stock_supplier_fast>
        <stock_supplier_slow>0</stock_supplier_slow>
        <total_stock>1</total_stock>
    </product>
    <product>
        <kodas>CT-R-BG002-BP</kodas>
        <ean>850036293156</ean>
        <stock_local>2</stock_local>
        <stock_supplier_fast>0</stock_supplier_fast>
        <stock_supplier_slow>0</stock_supplier_slow>
        <total_stock>2</total_stock>
    </product>
    <product>
        <kodas>KT5442WRD</kodas>
        <ean>4779030060617</ean>
        <stock_local>0</stock_local>
        <stock_supplier_fast>11</stock_supplier_fast>
        <stock_supplier_slow>0</stock_supplier_slow>
        <total_stock>11</total_stock>
    </product>
    <product>
        <kodas>L2222</kodas>
        <ean>3550839922228</ean>
        <stock_local>0</stock_local>
        <stock_supplier_fast>16</stock_supplier_fast>
        <stock_supplier_slow>0</stock_supplier_slow>
        <total_stock>16</total_stock>
    </product>
    <product>
        <kodas>L50052</kodas>
        <ean>3550833500521</ean>
        <stock_local>0</stock_local>
        <stock_supplier_fast>54</stock_supplier_fast>
        <stock_supplier_slow>0</stock_supplier_slow>
        <total_stock>54</total_stock>
    </product>
    <product>
        <kodas>L50056</kodas>
        <ean>3550833500569</ean>
        <stock_local>0</stock_local>
        <stock_supplier_fast>219</stock_supplier_fast>
        <stock_supplier_slow>0</stock_supplier_slow>
        <total_stock>219</total_stock>
    </product>
    <product>
        <kodas>L50057</kodas>
        <ean>3550833500576</ean>
        <stock_local>0</stock_local>
        <stock_supplier_fast>225</stock_supplier_fast>
        <stock_supplier_slow>0</stock_supplier_slow>
        <total_stock>225</total_stock>
    </product>
    <product>
        <kodas>MCB0001</kodas>
        <ean>0769807532014</ean>
        <stock_local>10</stock_local>
        <stock_supplier_fast>0</stock_supplier_fast>
        <stock_supplier_slow>0</stock_supplier_slow>
        <total_stock>10</total_stock>
    </product>
    <product>
        <kodas>MLTP-PW-DI-2-3</kodas>
        <ean>5060204032127</ean>
        <stock_local>0</stock_local>
        <stock_supplier_fast>6</stock_supplier_fast>
        <stock_supplier_slow>0</stock_supplier_slow>
        <total_stock>6</total_stock>
    </product>
    <product>
        <kodas>MT7101</kodas>
        <ean>191856071013</ean>
        <stock_local>0</stock_local>
        <stock_supplier_fast>6</stock_supplier_fast>
        <stock_supplier_slow>0</stock_supplier_slow>
        <total_stock>6</total_stock>
    </product>
    <product>
        <kodas>MT7206</kodas>
        <ean>191856072065</ean>
        <stock_local>0</stock_local>
        <stock_supplier_fast>191</stock_supplier_fast>
        <stock_supplier_slow>0</stock_supplier_slow>
        <total_stock>191</total_stock>
    </product>
    <product>
        <kodas>MT7309</kodas>
        <ean>191856073093</ean>
        <stock_local>0</stock_local>
        <stock_supplier_fast>195</stock_supplier_fast>
        <stock_supplier_slow>0</stock_supplier_slow>
        <total_stock>195</total_stock>
    </product>
    <product>
        <kodas>MT7513</kodas>
        <ean>191856075134</ean>
        <stock_local>0</stock_local>
        <stock_supplier_fast>306</stock_supplier_fast>
        <stock_supplier_slow>0</stock_supplier_slow>
        <total_stock>306</total_stock>
    </product>
    <product>
        <kodas>MT7743</kodas>
        <ean>191856077435</ean>
        <stock_local>0</stock_local>
        <stock_supplier_fast>175</stock_supplier_fast>
        <stock_supplier_slow>0</stock_supplier_slow>
        <total_stock>175</total_stock>
    </product>
    <product>
        <kodas>MT7918</kodas>
        <ean>191856079187</ean>
        <stock_local>0</stock_local>
        <stock_supplier_fast>190</stock_supplier_fast>
        <stock_supplier_slow>0</stock_supplier_slow>
        <total_stock>190</total_stock>
    </product>
    <product>
        <kodas>PN60136</kodas>
        <ean>4779030060136</ean>
        <stock_local>0</stock_local>
        <stock_supplier_fast>546</stock_supplier_fast>
        <stock_supplier_slow>0</stock_supplier_slow>
        <total_stock>546</total_stock>
    </product>
    <product>
        <kodas>PN60204</kodas>
        <ean>4779030060204</ean>
        <stock_local>0</stock_local>
        <stock_supplier_fast>597</stock_supplier_fast>
        <stock_supplier_slow>0</stock_supplier_slow>
        <total_stock>597</total_stock>
    </product>
    <product>
        <kodas>SP45614</kodas>
        <ean>5060639145614</ean>
        <stock_local>0</stock_local>
        <stock_supplier_fast>35</stock_supplier_fast>
        <stock_supplier_slow>0</stock_supplier_slow>
        <total_stock>35</total_stock>
    </product>
    <product>
        <kodas>SP45973</kodas>
        <ean>5060639145973</ean>
        <stock_local>0</stock_local>
        <stock_supplier_fast>49</stock_supplier_fast>
        <stock_supplier_slow>0</stock_supplier_slow>
        <total_stock>49</total_stock>
    </product>
    <product>
        <kodas>SP47618</kodas>
        <ean>5060639147618</ean>
        <stock_local>0</stock_local>
        <stock_supplier_fast>89</stock_supplier_fast>
        <stock_supplier_slow>0</stock_supplier_slow>
        <total_stock>89</total_stock>
    </product>
    <product>
        <kodas>SP47656</kodas>
        <ean>5060639147656</ean>
        <stock_local>0</stock_local>
        <stock_supplier_fast>29</stock_supplier_fast>
        <stock_supplier_slow>0</stock_supplier_slow>
        <total_stock>29</total_stock>
    </product>
    <product>
        <kodas>SP48189</kodas>
        <ean>5060639148189</ean>
        <stock_local>0</stock_local>
        <stock_supplier_fast>59</stock_supplier_fast>
        <stock_supplier_slow>0</stock_supplier_slow>
        <total_stock>59</total_stock>
    </product>
    <product>
        <kodas>SP48325</kodas>
        <ean>5060639148325</ean>
        <stock_local>0</stock_local>
        <stock_supplier_fast>24</stock_supplier_fast>
        <stock_supplier_slow>0</stock_supplier_slow>
        <total_stock>24</total_stock>
    </product>
    <product>
        <kodas>SP48332</kodas>
        <ean>5060639148332</ean>
        <stock_local>0</stock_local>
        <stock_supplier_fast>21</stock_supplier_fast>
        <stock_supplier_slow>0</stock_supplier_slow>
        <total_stock>21</total_stock>
    </product>
    <product>
        <kodas>SV03005</kodas>
        <ean>5208006030051</ean>
        <stock_local>0</stock_local>
        <stock_supplier_fast>39</stock_supplier_fast>
        <stock_supplier_slow>0</stock_supplier_slow>
        <total_stock>39</total_stock>
    </product>
    <product>
        <kodas>SV12512</kodas>
        <ean>5208006125122</ean>
        <stock_local>0</stock_local>
        <stock_supplier_fast>16</stock_supplier_fast>
        <stock_supplier_slow>0</stock_supplier_slow>
        <total_stock>16</total_stock>
    </product>
    <product>
        <kodas>SV12513</kodas>
        <ean>5208006125139</ean>
        <stock_local>0</stock_local>
        <stock_supplier_fast>18</stock_supplier_fast>
        <stock_supplier_slow>0</stock_supplier_slow>
        <total_stock>18</total_stock>
    </product>
    <product>
        <kodas>SV12514</kodas>
        <ean>5208006125146</ean>
        <stock_local>0</stock_local>
        <stock_supplier_fast>14</stock_supplier_fast>
        <stock_supplier_slow>0</stock_supplier_slow>
        <total_stock>14</total_stock>
    </product>
    <product>
        <kodas>SV13130A</kodas>
        <ean>5208006131307</ean>
        <stock_local>0</stock_local>
        <stock_supplier_fast>114</stock_supplier_fast>
        <stock_supplier_slow>0</stock_supplier_slow>
        <total_stock>114</total_stock>
    </product>
    <product>
        <kodas>SV13130B</kodas>
        <ean>5208006131307</ean>
        <stock_local>0</stock_local>
        <stock_supplier_fast>114</stock_supplier_fast>
        <stock_supplier_slow>0</stock_supplier_slow>
        <total_stock>114</total_stock>
    </product>
    <product>
        <kodas>SV13130C</kodas>
        <ean>5208006131307</ean>
        <stock_local>0</stock_local>
        <stock_supplier_fast>115</stock_supplier_fast>
        <stock_supplier_slow>0</stock_supplier_slow>
        <total_stock>115</total_stock>
    </product>
    <product>
        <kodas>SV13131</kodas>
        <ean>5208006131314</ean>
        <stock_local>0</stock_local>
        <stock_supplier_fast>287</stock_supplier_fast>
        <stock_supplier_slow>0</stock_supplier_slow>
        <total_stock>287</total_stock>
    </product>
    <product>
        <kodas>SV14073</kodas>
        <ean>5208006140736</ean>
        <stock_local>0</stock_local>
        <stock_supplier_fast>2</stock_supplier_fast>
        <stock_supplier_slow>0</stock_supplier_slow>
        <total_stock>2</total_stock>
    </product>
    <product>
        <kodas>SV23090</kodas>
        <ean>5208006230901</ean>
        <stock_local>0</stock_local>
        <stock_supplier_fast>18</stock_supplier_fast>
        <stock_supplier_slow>0</stock_supplier_slow>
        <total_stock>18</total_stock>
    </product>
    <product>
        <kodas>SV23091</kodas>
        <ean>5208006230918</ean>
        <stock_local>0</stock_local>
        <stock_supplier_fast>35</stock_supplier_fast>
        <stock_supplier_slow>0</stock_supplier_slow>
        <total_stock>35</total_stock>
    </product>
    <product>
        <kodas>SV23092</kodas>
        <ean>5208006230925</ean>
        <stock_local>0</stock_local>
        <stock_supplier_fast>21</stock_supplier_fast>
        <stock_supplier_slow>0</stock_supplier_slow>
        <total_stock>21</total_stock>
    </product>
    <product>
        <kodas>SV23131</kodas>
        <ean>5208006231311</ean>
        <stock_local>0</stock_local>
        <stock_supplier_fast>51</stock_supplier_fast>
        <stock_supplier_slow>0</stock_supplier_slow>
        <total_stock>51</total_stock>
    </product>
    <product>
        <kodas>SV23136</kodas>
        <ean>5208006231366</ean>
        <stock_local>0</stock_local>
        <stock_supplier_fast>8</stock_supplier_fast>
        <stock_supplier_slow>0</stock_supplier_slow>
        <total_stock>8</total_stock>
    </product>
    <product>
        <kodas>SV23137</kodas>
        <ean>5208006231373</ean>
        <stock_local>0</stock_local>
        <stock_supplier_fast>25</stock_supplier_fast>
        <stock_supplier_slow>0</stock_supplier_slow>
        <total_stock>25</total_stock>
    </product>
    <product>
        <kodas>SV23149</kodas>
        <ean>5208006231496</ean>
        <stock_local>0</stock_local>
        <stock_supplier_fast>14</stock_supplier_fast>
        <stock_supplier_slow>0</stock_supplier_slow>
        <total_stock>14</total_stock>
    </product>
    <product>
        <kodas>SV23305</kodas>
        <ean>5208006233056</ean>
        <stock_local>0</stock_local>
        <stock_supplier_fast>36</stock_supplier_fast>
        <stock_supplier_slow>0</stock_supplier_slow>
        <total_stock>36</total_stock>
    </product>
    <product>
        <kodas>SV23350</kodas>
        <ean>5208006233506</ean>
        <stock_local>0</stock_local>
        <stock_supplier_fast>15</stock_supplier_fast>
        <stock_supplier_slow>0</stock_supplier_slow>
        <total_stock>15</total_stock>
    </product>
    <product>
        <kodas>TEST-002</kodas>
        <stock_local>0</stock_local>
        <stock_supplier_fast>0</stock_supplier_fast>
        <stock_supplier_slow>0</stock_supplier_slow>
        <total_stock>0</total_stock>
    </product>
    <product>
        <kodas>TEST-003</kodas>
        <stock_local>0</stock_local>
        <stock_supplier_fast>0</stock_supplier_fast>
        <stock_supplier_slow>0</stock_supplier_slow>
        <total_stock>0</total_stock>
    </product>
    <product>
        <kodas>mari1547</kodas>
        <ean>5901435409701</ean>
        <stock_local>0</stock_local>
        <stock_supplier_fast>0</stock_supplier_fast>
        <stock_supplier_slow>0</stock_supplier_slow>
        <total_stock>0</total_stock>
    </product>
    <product>
        <kodas>mari1551</kodas>
        <ean>5901435412060</ean>
        <stock_local>0</stock_local>
        <stock_supplier_fast>0</stock_supplier_fast>
        <stock_supplier_slow>0</stock_supplier_slow>
        <total_stock>0</total_stock>
    </product>
    <product>
        <kodas>mari1562</kodas>
        <ean>5901435413746</ean>
        <stock_local>0</stock_local>
        <stock_supplier_fast>0</stock_supplier_fast>
        <stock_supplier_slow>0</stock_supplier_slow>
        <total_stock>0</total_stock>
    </product>
    <product>
        <kodas>mari1566</kodas>
        <ean>5901435409381</ean>
        <stock_local>0</stock_local>
        <stock_supplier_fast>0</stock_supplier_fast>
        <stock_supplier_slow>0</stock_supplier_slow>
        <total_stock>0</total_stock>
    </product>
</products>