<?xml version='1.0' encoding='utf-8'?>
<products>
    <product>
        <kodas>AR21582</kodas>
        <ean>8427614215828</ean>
        <stock_local>0</stock_local>
        <stock_supplier_fast>11</stock_supplier_fast>
        <stock_supplier_slow>0</stock_supplier_slow>
        <total_stock>11</total_stock>
    </product>
    <product>
        <kodas>L90110</kodas>
        <ean>3550833901106</ean>
        <stock_local>0</stock_local>
        <stock_supplier_fast>6</stock_supplier_fast>
        <stock_supplier_slow>0</stock_supplier_slow>
        <total_stock>6</total_stock>
    </product>
    <product>
        <kodas>MCP-LB</kodas>
        <ean>5060204030123</ean>
        <stock_local>0</stock_local>
        <stock_supplier_fast>24</stock_supplier_fast>
        <stock_supplier_slow>0</stock_supplier_slow>
        <total_stock>24</total_stock>
    </product>
</products>